ccpm/__main__.py
ccpm-0.0.1.dist-info/LICENSE.txt
ccpm-0.0.1.dist-info/METADATA
ccpm-0.0.1.dist-info/WHEEL
ccpm-0.0.1.dist-info/entry_points.txt
ccpm-0.0.1.dist-info/top_level.txt
ccpm-0.0.1.dist-info/RECORD
