Metadata-Version: 2.1
Name: ccpm
Version: 0.0.1
Summary: Custom Cmake Package Manager - Trying to bring 'npm' and 'pip' vibes to C++ (or any cmake project)
Author-email: Daniel Brétema <byBretema@gmail.com>
License: M.IT License
Project-URL: Repository, https://github.com/byBretema/ccpm.git
Keywords: cmake,cpp,c++,package,manager,package-manager
Classifier: Development Status :: 3 - Alpha
Classifier: Intended Audience :: Developers
Classifier: Topic :: Software Development :: Build Tools
Classifier: Programming Language :: Python :: 3
Classifier: License :: OSI Approved :: MIT License
Classifier: Operating System :: OS Independent
Requires-Python: >=3.8
License-File: LICENSE.txt
Requires-Dist: toml
